plate/__init__.py
plate/emojipedia.py
plate/languages.py
plate/plate.py
Plate-1.0.1.dist-info/LICENSE
Plate-1.0.1.dist-info/METADATA
Plate-1.0.1.dist-info/WHEEL
Plate-1.0.1.dist-info/top_level.txt
Plate-1.0.1.dist-info/RECORD
