Metadata-Version: 2.1
Name: Plate
Version: 1.0.1
Summary: Internationalization Library for Python
Home-page: https://github.com/delivrance/plate
Author: Dan
License: MIT
Project-URL: Tracker, https://github.com/delivrance/plate/issues
Project-URL: Source, https://github.com/delivrance/plate
Keywords: i18n internationalization l10n localization library python json interpolation pluralization emoji
Classifier: Development Status :: 5 - Production/Stable
Classifier: Intended Audience :: Developers
Classifier: License :: OSI Approved :: MIT License
Classifier: Operating System :: OS Independent
Classifier: Programming Language :: Python
Classifier: Programming Language :: Python :: 3
Classifier: Programming Language :: Python :: 3.7
Classifier: Programming Language :: Python :: 3.8
Classifier: Programming Language :: Python :: 3.9
Classifier: Programming Language :: Python :: 3.10
Classifier: Programming Language :: Python :: 3 :: Only
Classifier: Programming Language :: Python :: Implementation
Classifier: Programming Language :: Python :: Implementation :: CPython
Classifier: Programming Language :: Python :: Implementation :: PyPy
Classifier: Topic :: Software Development
Classifier: Topic :: Software Development :: Internationalization
Classifier: Topic :: Software Development :: Localization
Requires-Python: ~=3.7
License-File: LICENSE
